{"cameraMode":{"drawMode":0,"name":"Shaded","section":"Shading Mode"},"sceneLighting":true,"audioPlay":false,"sceneViewState":{"showFog":true,"showMaterialUpdate":false,"showSkybox":true,"showFlares":true,"showImageEffects":true,"showParticleSystems":true},"in2DMode":false,"pivot":{"x":-3.00748872756958,"y":-4.436368942260742,"z":2.0105533599853517},"rotation":{"x":-0.21694974601268769,"y":0.3145814538002014,"z":-0.07409167289733887,"w":-0.921131432056427},"size":14.664904594421387,"orthographic":false}